byteddorado_oapi/__init__.py
byteddorado_oapi-0.0.1.dist-info/METADATA
byteddorado_oapi-0.0.1.dist-info/WHEEL
byteddorado_oapi-0.0.1.dist-info/top_level.txt
byteddorado_oapi-0.0.1.dist-info/RECORD
